pash/__main.py
pash/pash.py
pash/shell_cmd.py
pash_py-0.3.0.dist-info/licenses/LICENSE
pash_py-0.3.0.dist-info/METADATA
pash_py-0.3.0.dist-info/WHEEL
pash_py-0.3.0.dist-info/top_level.txt
pash_py-0.3.0.dist-info/RECORD
