Metadata-Version: 2.4
Name: pash-py
Version: 0.3.0
Summary: Run shell commands with python
Author-email: Mina Kamel <minallkamel@gmail.com>
License: MIT License
License-File: LICENSE
Dynamic: license-file
